hya/__init__.py
hya/braceexpand.py
hya/default.py
hya/imports.py
hya/numpy.py
hya/py.typed
hya/registry.py
hya/resolvers.py
hya/testing.py
hya/torch.py
hya/utils/__init__.py
hya/utils/fallback/__init__.py
hya/utils/fallback/braceexpand.py
hya/utils/fallback/numpy.py
hya/utils/fallback/torch.py
hya-0.4.0.dist-info/METADATA
hya-0.4.0.dist-info/WHEEL
hya-0.4.0.dist-info/licenses/LICENSE
hya-0.4.0.dist-info/RECORD
