Metadata-Version: 2.4
Name: hya
Version: 0.4.0
Dynamic: Maintainer
Dynamic: Maintainer-email
Summary: A library of custom OmegaConf resolvers
Project-URL: homepage, https://github.com/durandtibo/hya
Project-URL: repository, https://github.com/durandtibo/hya
Project-URL: documentation, https://durandtibo.github.io/hya/
Author-email: Thibaut Durand <durand.tibo+gh@gmail.com>
License-Expression: BSD-3-Clause
License-File: LICENSE
Keywords: hydra,omegaconf,resolver
Classifier: Development Status :: 4 - Beta
Classifier: Intended Audience :: Developers
Classifier: Intended Audience :: Information Technology
Classifier: Intended Audience :: Science/Research
Classifier: License :: OSI Approved :: BSD License
Classifier: Operating System :: POSIX :: Linux
Classifier: Programming Language :: Python :: 3.10
Classifier: Programming Language :: Python :: 3.11
Classifier: Programming Language :: Python :: 3.12
Classifier: Programming Language :: Python :: 3.13
Classifier: Programming Language :: Python :: 3.14
Classifier: Topic :: Scientific/Engineering
Classifier: Topic :: Software Development :: Libraries
Requires-Python: >=3.10
Requires-Dist: omegaconf<3.0,>=2.2
Provides-Extra: all
Requires-Dist: braceexpand<0.2.0,>=0.1.7; extra == 'all'
Requires-Dist: numpy<3.0,>=1.24; extra == 'all'
Requires-Dist: torch<2.3,>=2.0; (sys_platform == 'darwin' and platform_machine != 'arm64' and python_version < '3.13') and extra == 'all'
Requires-Dist: torch<3.0,>=2.0; (sys_platform == 'linux' or (sys_platform == 'darwin' and platform_machine == 'arm64')) and extra == 'all'
Provides-Extra: braceexpand
Requires-Dist: braceexpand<0.2.0,>=0.1.7; extra == 'braceexpand'
Provides-Extra: numpy
Requires-Dist: numpy<3.0,>=1.24; extra == 'numpy'
Provides-Extra: torch
Requires-Dist: torch<2.3,>=2.0; (sys_platform == 'darwin' and platform_machine != 'arm64' and python_version < '3.13') and extra == 'torch'
Requires-Dist: torch<3.0,>=2.0; (sys_platform == 'linux' or (sys_platform == 'darwin' and platform_machine == 'arm64')) and extra == 'torch'
